[{"__type__":"cc.SpriteFrame","content":{"name":"game_atlas0369","texture":"9fA+AMNplPu7TWL9tC51oV","rect":[0,0,120,47],"offset":[0,0],"originalSize":[120,47],"capInsets":[40,14,42,22]}},{"__type__":"cc.SpriteFrame","content":{"name":"answer","texture":"1exOVX3q1NKbjwfT+tZtUQ","rect":[2,1,89,38],"offset":[-0.5,0],"originalSize":[94,40],"capInsets":[0,0,0,0]}},{"__type__":"cc.SpriteFrame","content":{"name":"game_atlas0233","texture":"3en4hV24dO8bhxisa8rjIn","rect":[0,0,68,68],"offset":[0,0],"originalSize":[68,68],"capInsets":[0,0,0,0]}},{"__type__":"cc.SpriteFrame","content":{"name":"game_atlas0443","texture":"4ckMEI4JVDIrqx+Lg5G24p","rect":[0,0,37,37],"offset":[0,0],"originalSize":[37,37],"capInsets":[0,0,0,0]}},{"__type__":"cc.SpriteFrame","content":{"name":"default_sprite_splash","texture":"02delMVqdBD70a/HSD99FK","rect":[0,0,2,2],"offset":[0,0],"originalSize":[2,2],"capInsets":[0,0,0,0]}},{"__type__":"cc.SpriteFrame","content":{"name":"game_atlas0203","texture":"71pQe0nTFGs79HnMcDnrdC","rect":[0,0,215,85],"offset":[0,0],"originalSize":[215,85],"capInsets":[92,27,92,33]}},{"__type__":"cc.SpriteFrame","content":{"name":"game_atlas0265","texture":"3dLLNa/vdLJrQzYZdvlwwz","rect":[0,0,190,242],"offset":[0,0],"originalSize":[190,242],"capInsets":[77,102,79,104]}},[{"__type__":"cc.Prefab","_name":"TipsNode","data":{"__id__":1}},{"__type__":"cc.Node","_name":"TipsNode","_children":[{"__id__":2},{"__id__":3}],"_level":1,"_components":[{"__type__":"cc.BlockInputEvents","node":{"__id__":1}},{"__type__":"cc.Widget","node":{"__id__":1},"_alignFlags":45,"_originalWidth":750,"_originalHeight":1334},{"__type__":"1f0e1ZGZWZIo6/bDxTPKHHJ","node":{"__id__":1}}],"_prefab":{"__type__":"cc.PrefabInfo","root":{"__id__":1},"asset":{"__uuid__":"cf7hsX3bFJA5wGtclK6vsw"},"fileId":"1bAJDO4hVGTqX/mxOH19AE"},"_contentSize":{"__type__":"cc.Size","width":750,"height":1334},"_position":{"__type__":"cc.Vec3","x":375,"y":667},"_scale":{"__type__":"cc.Vec3","x":1,"y":1,"z":1}},{"__type__":"cc.Node","_name":"bg","_parent":{"__id__":1},"_level":2,"_components":[{"__type__":"cc.Sprite","node":{"__id__":2},"_spriteFrame":{"__uuid__":"a2MjXRFdtLlYQ5ouAFv/+R"},"_sizeMode":0},{"__type__":"cc.Button","node":{"__id__":2}},{"__type__":"cc.Widget","node":{"__id__":2},"_alignFlags":45,"_originalWidth":750,"_originalHeight":1334}],"_prefab":{"__type__":"cc.PrefabInfo","root":{"__id__":1},"asset":{"__uuid__":"cf7hsX3bFJA5wGtclK6vsw"},"fileId":"degoRr86BKeLSFp+lRRHax"},"_opacity":220,"_color":{"__type__":"cc.Color"},"_contentSize":{"__type__":"cc.Size","width":750,"height":1334},"_scale":{"__type__":"cc.Vec3","x":1,"y":1,"z":1}},{"__type__":"cc.Node","_name":"framebg","_parent":{"__id__":1},"_children":[{"__id__":4},{"__id__":5},{"__id__":8},{"__id__":9},{"__id__":10},{"__id__":11},{"__id__":12},{"__id__":13}],"_level":2,"_components":[{"__type__":"cc.Sprite","node":{"__id__":3},"_spriteFrame":{"__uuid__":"c7Mtk1mJ5A2pf1Gd87T9+U"},"_type":1,"_sizeMode":0}],"_prefab":{"__type__":"cc.PrefabInfo","root":{"__id__":1},"asset":{"__uuid__":"cf7hsX3bFJA5wGtclK6vsw"},"fileId":"e6Je/nCxpNAJKQ1Y0rWEIK"},"_contentSize":{"__type__":"cc.Size","width":680,"height":600},"_scale":{"__type__":"cc.Vec3","x":1,"y":1,"z":1}},{"__type__":"cc.Node","_name":"xuxiankuan","_parent":{"__id__":3},"_active":false,"_level":3,"_components":[{"__type__":"cc.Sprite","node":{"__id__":4},"_spriteFrame":{"__uuid__":"d7lESYf/ZB6bSwfHka0Pf9"},"_sizeMode":0}],"_prefab":{"__type__":"cc.PrefabInfo","root":{"__id__":1},"asset":{"__uuid__":"cf7hsX3bFJA5wGtclK6vsw"},"fileId":"8dXeQbNEJLEIkJmJuUfT0G"},"_contentSize":{"__type__":"cc.Size","width":640,"height":270},"_position":{"__type__":"cc.Vec3","y":13},"_scale":{"__type__":"cc.Vec3","x":1,"y":1,"z":1}},{"__type__":"cc.Node","_name":"getkeyBtn","_parent":{"__id__":3},"_children":[{"__id__":6},{"__id__":7}],"_level":3,"_components":[{"__type__":"cc.Sprite","node":{"__id__":5},"_spriteFrame":{"__uuid__":"bbkowtyXVLcavsGXR3YxVU"},"_sizeMode":0},{"__type__":"cc.Button","node":{"__id__":5},"zoomScale":0.8,"_N$transition":3,"transition":3}],"_prefab":{"__type__":"cc.PrefabInfo","root":{"__id__":1},"asset":{"__uuid__":"cf7hsX3bFJA5wGtclK6vsw"},"fileId":"2667mdvGtFj4NpdBXs0d56"},"_contentSize":{"__type__":"cc.Size","width":230,"height":94},"_position":{"__type__":"cc.Vec3","y":-205},"_scale":{"__type__":"cc.Vec3","x":1,"y":1,"z":1}},{"__type__":"cc.Node","_name":"New Label","_parent":{"__id__":5},"_level":4,"_components":[{"__type__":"cc.Label","node":{"__id__":6},"_useOriginalSize":false,"_string":"获取能量","_N$string":"获取能量","_N$file":{"__uuid__":"09MebMuTtOpILKMpe07ZFQ"},"_isSystemFontUsed":false,"_N$horizontalAlign":1,"_N$verticalAlign":1}],"_prefab":{"__type__":"cc.PrefabInfo","root":{"__id__":1},"asset":{"__uuid__":"cf7hsX3bFJA5wGtclK6vsw"},"fileId":"5925jRWsNNk7VHlSF2Mjnt"},"_color":{"__type__":"cc.Color","r":16,"g":59,"b":35},"_contentSize":{"__type__":"cc.Size","width":160.73,"height":29.09},"_position":{"__type__":"cc.Vec3","x":19.379,"y":6.365},"_scale":{"__type__":"cc.Vec3","x":1,"y":1,"z":1}},{"__type__":"cc.Node","_name":"game_atlas0443","_parent":{"__id__":5},"_level":4,"_components":[{"__type__":"cc.Sprite","node":{"__id__":7},"_spriteFrame":{"__uuid__":"975sfuqw1MK7M3WgTWHRt2"}}],"_prefab":{"__type__":"cc.PrefabInfo","root":{"__id__":1},"asset":{"__uuid__":"cf7hsX3bFJA5wGtclK6vsw"},"fileId":"9fXZtjyOdCeJD7PEGMpsFX"},"_contentSize":{"__type__":"cc.Size","width":37,"height":37},"_position":{"__type__":"cc.Vec3","x":-85.592},"_scale":{"__type__":"cc.Vec3","x":1,"y":1,"z":1}},{"__type__":"cc.Node","_name":"board","_parent":{"__id__":3},"_level":3,"_components":[{"__type__":"cc.Sprite","node":{"__id__":8},"_spriteFrame":{"__uuid__":"12GVI049hCN7Qtf2JkwzPY"},"_type":1,"_sizeMode":0}],"_prefab":{"__type__":"cc.PrefabInfo","root":{"__id__":1},"asset":{"__uuid__":"cf7hsX3bFJA5wGtclK6vsw"},"fileId":"b5GYKiYrJBlqNShZp4bQhy"},"_contentSize":{"__type__":"cc.Size","width":640,"height":280},"_position":{"__type__":"cc.Vec3","y":7.134},"_scale":{"__type__":"cc.Vec3","x":1,"y":1,"z":1}},{"__type__":"cc.Node","_name":"tipsinfo","_parent":{"__id__":3},"_level":3,"_components":[{"__type__":"cc.Label","node":{"__id__":9},"_useOriginalSize":false,"_fontSize":50,"_lineHeight":60,"_N$horizontalAlign":1,"_N$verticalAlign":1,"_N$overflow":3},{"__type__":"cc.LabelOutline","node":{"__id__":9},"_color":{"__type__":"cc.Color","r":59,"g":45,"b":8}}],"_prefab":{"__type__":"cc.PrefabInfo","root":{"__id__":1},"asset":{"__uuid__":"cf7hsX3bFJA5wGtclK6vsw"},"fileId":"33gqD/1S5B/qrjCSC1TK3G"},"_color":{"__type__":"cc.Color","r":51,"g":32,"b":11},"_contentSize":{"__type__":"cc.Size","width":600,"height":77.6},"_position":{"__type__":"cc.Vec3","y":4},"_scale":{"__type__":"cc.Vec3","x":1,"y":1,"z":1}},{"__type__":"cc.Node","_name":"answer","_parent":{"__id__":3},"_active":false,"_level":3,"_components":[{"__type__":"cc.Sprite","node":{"__id__":10},"_spriteFrame":{"__uuid__":"3c+uMeJmJJJLvep/NS8RRM"}}],"_prefab":{"__type__":"cc.PrefabInfo","root":{"__id__":1},"asset":{"__uuid__":"cf7hsX3bFJA5wGtclK6vsw"},"fileId":"deSBY8zQFC2rv3Z7xWt6wW"},"_contentSize":{"__type__":"cc.Size","width":89,"height":38},"_position":{"__type__":"cc.Vec3","x":-203,"y":225},"_scale":{"__type__":"cc.Vec3","x":2,"y":2,"z":1}},{"__type__":"cc.Node","_name":"closebtn","_parent":{"__id__":3},"_level":3,"_components":[{"__type__":"cc.Sprite","node":{"__id__":11},"_spriteFrame":{"__uuid__":"47Pl1gGxhKwpCvIR+s6/G4"}},{"__type__":"cc.Button","node":{"__id__":11},"zoomScale":0.8,"_N$transition":3,"transition":3}],"_prefab":{"__type__":"cc.PrefabInfo","root":{"__id__":1},"asset":{"__uuid__":"cf7hsX3bFJA5wGtclK6vsw"},"fileId":"97NKuhoO9P46OKUkzzrTjh"},"_contentSize":{"__type__":"cc.Size","width":68,"height":68},"_position":{"__type__":"cc.Vec3","x":306,"y":283},"_scale":{"__type__":"cc.Vec3","x":1,"y":1,"z":1}},{"__type__":"cc.Node","_name":"title","_parent":{"__id__":3},"_level":3,"_components":[{"__type__":"cc.Label","node":{"__id__":12},"_useOriginalSize":false,"_string":"答案","_N$string":"答案","_N$file":{"__uuid__":"09MebMuTtOpILKMpe07ZFQ"},"_isSystemFontUsed":false,"_N$horizontalAlign":1,"_N$verticalAlign":1}],"_prefab":{"__type__":"cc.PrefabInfo","root":{"__id__":1},"asset":{"__uuid__":"cf7hsX3bFJA5wGtclK6vsw"},"fileId":"f0xThObvJEk7AR6smVp7Ay"},"_color":{"__type__":"cc.Color","r":241,"g":200,"b":111},"_contentSize":{"__type__":"cc.Size","width":79.27,"height":29.09},"_position":{"__type__":"cc.Vec3","y":384.87},"_scale":{"__type__":"cc.Vec3","x":1.5,"y":1.5,"z":1}},{"__type__":"cc.Node","_name":"tips","_parent":{"__id__":3},"_children":[{"__id__":14}],"_level":3,"_components":[{"__type__":"cc.Label","node":{"__id__":13},"_useOriginalSize":false,"_string":"消耗      X1","_N$string":"消耗      X1","_N$horizontalAlign":1,"_N$verticalAlign":1}],"_prefab":{"__type__":"cc.PrefabInfo","root":{"__id__":1},"asset":{"__uuid__":"cf7hsX3bFJA5wGtclK6vsw"},"fileId":"96y3JpaqFJhaGQ35JSCdJM"},"_color":{"__type__":"cc.Color","r":37,"g":29,"b":6},"_contentSize":{"__type__":"cc.Size","width":195.61,"height":50.4},"_position":{"__type__":"cc.Vec3","y":207.826},"_scale":{"__type__":"cc.Vec3","x":1,"y":1,"z":1}},{"__type__":"cc.Node","_name":"dengpao","_parent":{"__id__":13},"_level":4,"_components":[{"__type__":"cc.Sprite","node":{"__id__":14},"_spriteFrame":{"__uuid__":"f5ZJWKv99GKKVndQI+JwdD"}}],"_prefab":{"__type__":"cc.PrefabInfo","root":{"__id__":1},"asset":{"__uuid__":"cf7hsX3bFJA5wGtclK6vsw"},"fileId":"79qU9WdPpJa7lqF/hJEgof"},"_contentSize":{"__type__":"cc.Size","width":54,"height":78},"_position":{"__type__":"cc.Vec3","x":22.949,"y":5.566},"_scale":{"__type__":"cc.Vec3","x":0.7,"y":0.7,"z":1}}],{"__type__":"cc.SpriteFrame","content":{"name":"xuxiankuan","texture":"edUwJeJOFJWILQrjH7hTj/","rect":[0,0,526,336],"offset":[0,0],"originalSize":[526,336],"capInsets":[0,0,0,0]}},{"__type__":"cc.SpriteFrame","content":{"name":"dengpao","texture":"41F/vf6ehFb7gNTHuJ0CDZ","rect":[0,2,54,77],"offset":[0,-1],"originalSize":[54,79],"capInsets":[0,0,0,0]}}]