{"__type__":"cc.SpriteAtlas","_spriteFrames":{"image_Boom":{"__uuid__":"2czVvwlexCxp1jv/ze0hQL"},"image_BoomB":{"__uuid__":"36S3ylJHdFTaVqNZreGDWP"},"image_CircleBoom":{"__uuid__":"3fDU1ALSpAvrM3jabiURZd"},"image_BoomY":{"__uuid__":"4fcAXKJq5Px6KIreoTBMXj"},"image_RedBoom":{"__uuid__":"60vqqTdoJIPZb1tvC8GaFD"},"image_PurpleBoom":{"__uuid__":"781rx5y01KjafLX3H66juf"},"image_BoomG":{"__uuid__":"9dbQoHfUVGiYzoIwtUekdJ"},"image_Box":{"__uuid__":"9eyygZzpFEGI4hagh80BRq"},"image_BlueBoom":{"__uuid__":"c9zcnX7EFPZoOhLbLr0c1f"},"image_GreenBoom":{"__uuid__":"e8qP04dd5E6rs4+ZJiFPmm"}}}