{"__type__":"cc.JsonAsset","_name":"level_38","json":{"sun_data":[],"earth_data":[],"role_data":[{"type":1,"posX":-220,"posY":-153,"width":70,"height":148,"angle":0,"anchorX":0.5,"anchorY":0.5,"moveDirection":null,"moveRangeY":null,"moveRangeX":null,"moveSpeed":null,"connectBody":null,"target":null,"phyWidth":null,"phyHeight":null,"enabledContact":null,"density":null,"ropeNums":null}],"enemy_data":[{"type":1,"posX":172,"posY":-157,"width":0,"height":0,"angle":0,"anchorX":0.5,"anchorY":0.5,"moveDirection":null,"moveRangeY":null,"moveRangeX":null,"moveSpeed":null,"connectBody":null,"target":null,"phyWidth":null,"phyHeight":null,"enabledContact":null,"density":null,"ropeNums":null}],"back_data":[{"type":3,"posX":-31,"posY":-477,"width":800,"height":500,"angle":7.016709298534876e-15,"anchorX":0.5,"anchorY":0.5,"moveDirection":null,"moveRangeY":null,"moveRangeX":null,"moveSpeed":null,"connectBody":null,"target":null,"phyWidth":null,"phyHeight":null,"enabledContact":null,"density":null,"ropeNums":null}],"block_data":[{"type":3,"posX":0,"posY":-81,"width":80,"height":250,"angle":0,"anchorX":0.5,"anchorY":0.5,"moveDirection":null,"moveRangeY":null,"moveRangeX":null,"moveSpeed":null,"connectBody":"block","target":null,"phyWidth":null,"phyHeight":null,"enabledContact":null,"density":0.06,"ropeNums":null}],"moveBlock_data":[],"boom_data":[],"box_data":[],"tu_data":[{"type":3,"posX":-31,"posY":-477,"width":760,"height":460,"angle":7.016709298534876e-15,"anchorX":0.5,"anchorY":0.5,"moveDirection":null,"moveRangeY":null,"moveRangeX":null,"moveSpeed":null,"connectBody":null,"target":null,"phyWidth":null,"phyHeight":null,"enabledContact":null,"density":null,"ropeNums":null}],"staticTex_data":[],"axle_data":[{"type":3,"posX":0,"posY":13,"width":16,"height":16,"angle":0,"anchorX":0.5,"anchorY":0.5,"moveDirection":null,"moveRangeY":null,"moveRangeX":null,"moveSpeed":null,"connectBody":"block","target":null,"phyWidth":null,"phyHeight":null,"enabledContact":null,"density":null,"ropeNums":null}],"ball_data":[],"crossBall_data":[],"crossBlock_data":[],"grenade_data":[],"magicBox_data":[],"rope_data":[],"vip_data":[],"switch_data":[]}}